dtgui/__init__.py
dtgui/__main__.py
dtgui/batch.py
dtgui/control_bar.py
dtgui/controller.py
dtgui/dataviewer.py
dtgui/error_aware.py
dtgui/gui.py
dtgui-1.1.2.dist-info/DESCRIPTION.rst
dtgui-1.1.2.dist-info/METADATA
dtgui-1.1.2.dist-info/RECORD
dtgui-1.1.2.dist-info/WHEEL
dtgui-1.1.2.dist-info/entry_points.txt
dtgui-1.1.2.dist-info/metadata.json
dtgui-1.1.2.dist-info/top_level.txt
