Metadata-Version: 2.0
Name: dtgui
Version: 1.1.2
Summary: GUI baseline-subtraction using the dual-tree complex wavelet transform
Home-page: http://www.physics.mcgill.ca/siwicklab/software.html
Author: Laurent P. René de Cotret
Author-email: laurent.renedecotret@mail.mcgill.ca
License: MIT
Download-URL: http://github.com/LaurentRDC/dtgui
Keywords: dtgui
Platform: UNKNOWN
Classifier: Intended Audience :: Science/Research
Classifier: Topic :: Scientific/Engineering
Classifier: Topic :: Scientific/Engineering :: Visualization
Classifier: License :: OSI Approved :: MIT License
Classifier: Natural Language :: English
Classifier: Operating System :: OS Independent
Classifier: Programming Language :: Python
Classifier: Programming Language :: Python :: 3.5
Classifier: Programming Language :: Python :: 3.6
Requires-Dist: numpy (>=1.12)
Requires-Dist: pyqtgraph (>=0.10)
Requires-Dist: scikit-ued (>=0.4.9)
Requires-Dist: pyqt5
Requires-Dist: pywavelets (>=0.5.2)
Requires-Dist: qdarkstyle (>=2.3.1)
